peptidy/__init__.py
peptidy/biology.py
peptidy/descriptors.py
peptidy/encoding.py
peptidy/tokenizer.py
peptidy/data/aromatic_aas.json
peptidy/data/blosum62_scores.json
peptidy/data/descriptor_per_aas.json
peptidy/data/formulas.json
peptidy/data/hydrophobic_aas.json
peptidy/data/instabilities.json
peptidy/data/n_h_acceptors.json
peptidy/data/n_h_donors.json
peptidy/data/n_rotatable_bonds.json
peptidy/data/neg_pks.json
peptidy/data/pos_pks.json
peptidy/data/token_to_label.json
peptidy/data/tpsas.json
peptidy/data/weights.json
peptidy/data/x_logps.json
peptidy-0.0.1.dist-info/LICENSE
peptidy-0.0.1.dist-info/METADATA
peptidy-0.0.1.dist-info/WHEEL
peptidy-0.0.1.dist-info/top_level.txt
peptidy-0.0.1.dist-info/RECORD
