Metadata-Version: 2.1
Name: peptidy
Version: 0.0.1
Summary: A Python library that converts peptide sequences to matrices for machine learning.
Home-page: https://molml.github.io/peptidy/
Author: Rıza Özçelik
Author-email: r.ozcelik@tue.nl
License: MIT
Project-URL: Bug Reports, https://molml.github.io/peptidy/issues/
Project-URL: Documentation, https://molml.github.io/peptidy/
Project-URL: Source, https://molml.github.io/peptidy/
Keywords: peptides,proteins,descriptors,machine learning,deep learning
Classifier: Development Status :: 3 - Alpha
Classifier: Intended Audience :: Developers
Classifier: License :: OSI Approved :: MIT License
Classifier: Operating System :: OS Independent
Classifier: Programming Language :: Python :: 3
Classifier: Programming Language :: Python :: 3.7
Classifier: Programming Language :: Python :: 3.8
Classifier: Programming Language :: Python :: 3.9
Classifier: Programming Language :: Python :: 3.10
Classifier: Programming Language :: Python :: 3 :: Only
Classifier: Intended Audience :: Science/Research
Requires-Python: >=3.6, <4
License-File: LICENSE
